<?xml version="1.0" ?>
<ModelUnit modelid=".SoilTemperatureSWAT model" name="SoilTemperatureSWAT model" timestep="1" version="001">
	<Description>
		<Title>SoilTemperatureSWAT model</Title>
		<Authors>Simone Bregaglio</Authors>
		<Institution>University of Milan</Institution>
		<URI>http://swatmodel.tamu.edu/media/1290/swat2000theory.pdf</URI>
		<Reference>-</Reference>
		<ExtendedDescription>Implements the SWAT method to compute soil temperature by layers with a daily time step. The approach uses layer thickness, bulk density, volumetric water content, and an annual average air temperature to compute maximum damping depth, a scaling factor, and depth factors, then applies a lagged update to each layer’s temperature. The surface soil temperature is computed via the SWAT surface energy balance proxy and used with a lag coefficient to update the profile. References: SWAT Theoretical Documentation (Version 2000): http://swatmodel.tamu.edu/media/1290/swat2000theory.pdf; JRC MARS biophysical domain ontology: http://bioma.jrc.ec.europa.eu/ontology/JRC_MARS_biophysical_domain.owl</ExtendedDescription>
		<ShortDescription>Calculates soil temperature by layers using the SWAT method with lagged daily updates.</ShortDescription>
	</Description>
	<Inputs>
		<Input name="LayerThickness" description="Soil layer thickness" inputtype="parameter" parametercategory="constant" datatype="DOUBLELIST" len="-" max="-" min="-" default="-" unit="m" uri="-"/>
		<Input name="ex_VolumetricWaterContent" description="Volumetric soil water content" inputtype="variable" variablecategory="exogenous" datatype="DOUBLELIST" len="-" max="-" min="-" default="-" unit="m3 m-3" uri="-"/>
		<Input name="a_SurfaceSoilTemperature" description="Average surface soil temperature" inputtype="variable" variablecategory="exogenous" datatype="DOUBLE" max="-" min="-" default="-" unit="degC" uri="-"/>
		<Input name="s_SoilTemperatureByLayers" description="Previous day's soil temperature of each layer" inputtype="variable" variablecategory="state" datatype="DOUBLELIST" len="-" max="-" min="-" default="-" unit="degC" uri="-"/>
		<Input name="LagCoefficient" description="Lag coefficient" inputtype="parameter" parametercategory="constant" datatype="DOUBLE" max="-" min="-" default="-" unit="-" uri="-"/>
		<Input name="AirTemperatureAnnualAverage" description="Annual average air temperature" inputtype="parameter" parametercategory="constant" datatype="DOUBLE" max="-" min="-" default="-" unit="degC" uri="-"/>
		<Input name="BulkDensity" description="Bulk density" inputtype="parameter" parametercategory="constant" datatype="DOUBLELIST" len="-" max="-" min="-" default="-" unit="t m-3" uri="-"/>
		<Input name="SoilProfileDepth" description="Soil profile depth" inputtype="parameter" parametercategory="constant" datatype="DOUBLE" max="-" min="-" default="-" unit="m" uri="-"/>
	</Inputs>
	<Outputs>
		<Output name="SoilTemperatureByLayers" description="Updated soil temperature of each layer" variablecategory="state" datatype="DOUBLELIST" len="-" max="-" min="-" unit="degC" uri="-"/>
	</Outputs>
	<Initialization name="Init" language="cyml" filename="algo/pyx/Init.pyx"/>
	<Function name="-" description="-" language="cyml" type="external" filename="algo/pyx/-.pyx"/>
	<Algorithm language="cyml" platform="" filename="algo/pyx/CalculateModel.pyx"/>
	<Parametersets/>
	<Testsets/>
</ModelUnit>
